{
  "$schema": "http://json-schema.org/draft-04/schema#",
  "title": "FileRouted.v1",
  "description": "A processing object has been moved to clean, quarantine or investigation according to its GuardDuty scan result and the matching object tag breadcrumb.",
  "type": "object",
  "additionalProperties": false,
  "required": [
    "version",
    "id",
    "detail-type",
    "source",
    "account",
    "time",
    "region",
    "detail"
  ],
  "properties": {
    "version": { "type": "string", "enum": ["0"] },
    "id": { "type": "string", "format": "uuid" },
    "detail-type": { "type": "string", "enum": ["FileRouted.v1"] },
    "source": {
      "type": "string",
      "enum": ["uk.gov.justice.service.managed-file-transfer"]
    },
    "account": { "type": "string", "pattern": "^[0-9]{12}$" },
    "time": { "type": "string", "format": "date-time" },
    "region": { "type": "string" },
    "resources": { "type": "array", "items": { "type": "string" } },
    "replay-name": { "type": "string", "minLength": 1 },
    "detail": {
      "type": "object",
      "additionalProperties": false,
      "required": ["metadata", "data"],
      "properties": {
        "metadata": { "$ref": "#/definitions/eventMetadata" },
        "data": {
          "type": "object",
          "additionalProperties": false,
          "required": [
            "fileId",
            "sourceObject",
            "destinationObject",
            "route",
            "scanResultStatus",
            "scanResultStatusMatchesTag",
            "sourceDeleted"
          ],
          "oneOf": [
            {
              "properties": {
                "route": { "enum": ["clean"] },
                "scanResultStatus": { "enum": ["NO_THREATS_FOUND"] },
                "scanResultStatusMatchesTag": { "enum": [true] }
              }
            },
            {
              "properties": {
                "route": { "enum": ["quarantine"] },
                "scanResultStatus": { "enum": ["THREATS_FOUND"] },
                "scanResultStatusMatchesTag": { "enum": [true] }
              }
            },
            {
              "properties": {
                "route": { "enum": ["investigation"] }
              },
              "anyOf": [
                {
                  "properties": {
                    "scanResultStatusMatchesTag": { "enum": [false] }
                  }
                },
                {
                  "properties": {
                    "scanResultStatus": {
                      "enum": ["UNSUPPORTED", "ACCESS_DENIED", "FAILED"]
                    }
                  }
                }
              ]
            }
          ],
          "properties": {
            "fileId": {
              "type": "string",
              "format": "uuid",
              "description": "Stable logical file identifier inherited from FileReceived.v1."
            },
            "sourceObject": { "$ref": "#/definitions/s3Object" },
            "destinationObject": { "$ref": "#/definitions/s3Object" },
            "route": {
              "type": "string",
              "enum": ["clean", "quarantine", "investigation"]
            },
            "scanResultStatus": {
              "type": "string",
              "enum": [
                "NO_THREATS_FOUND",
                "THREATS_FOUND",
                "UNSUPPORTED",
                "ACCESS_DENIED",
                "FAILED"
              ]
            },
            "scanResultStatusMatchesTag": {
              "type": "boolean"
            },
            "sourceDeleted": { "type": "boolean", "enum": [true] }
          }
        }
      }
    }
  },
  "definitions": {
    "eventMetadata": {
      "type": "object",
      "additionalProperties": false,
      "required": ["correlationId", "causationId", "idempotencyKey"],
      "properties": {
        "correlationId": { "type": "string", "format": "uuid" },
        "causationId": { "type": "string", "format": "uuid" },
        "idempotencyKey": { "type": "string", "minLength": 1 }
      }
    },
    "s3Object": {
      "type": "object",
      "additionalProperties": false,
      "description": "A particular version of an object stored in Amazon S3.",
      "required": ["bucket", "key", "versionId", "sizeBytes"],
      "properties": {
        "bucket": { "type": "string", "minLength": 3 },
        "key": { "type": "string", "minLength": 1 },
        "versionId": { "type": "string", "minLength": 1 },
        "sizeBytes": { "type": "integer", "minimum": 0 }
      }
    }
  },
  "examples": [
    {
      "version": "0",
      "id": "aa88e95a-159c-40c1-9e7b-38d00b0b6169",
      "detail-type": "FileRouted.v1",
      "source": "uk.gov.justice.service.managed-file-transfer",
      "account": "123456789012",
      "time": "2026-07-10T14:03:00Z",
      "region": "eu-west-2",
      "detail": {
        "metadata": {
          "correlationId": "7d9f4e4c-0e0f-4a5b-8b4e-4ab1f28fd1d1",
          "causationId": "c5dc9cb4-3b1f-4f01-a4c6-41b30e11d790",
          "idempotencyKey": "route:clean:clean:example/report.csv:5Ni..."
        },
        "data": {
          "fileId": "3f4e3d7a-4e2f-4bc2-9c4e-5f1ef2d4c501",
          "sourceObject": {
            "bucket": "processing",
            "key": "example/report.csv",
            "versionId": "4Mh...",
            "sizeBytes": 4096
          },
          "destinationObject": {
            "bucket": "clean",
            "key": "example/report.csv",
            "versionId": "5Ni...",
            "sizeBytes": 4096
          },
          "route": "clean",
          "scanResultStatus": "NO_THREATS_FOUND",
          "scanResultStatusMatchesTag": true,
          "sourceDeleted": true
        }
      }
    }
  ]
}
